{"indLibelle":"Production en quantité des produits miniers","metaData":{"decription":null,"periodicite":"Annuelle","unite":"TONNE","source":"MINISTERE DE L'ENERGIE ET DES MINES, DE L'EAU ET DE L'ENVIRONNEMENT "},"periodes":["2012","2013","2014","2015","2016","2017"],"levels":[{"serie":{"data":[{"valeur":null,"annee":"2012"},{"valeur":null,"annee":"2013"},{"valeur":null,"annee":"2014"},{"valeur":null,"annee":"2015"},{"valeur":null,"annee":"2016"},{"valeur":null,"annee":"2017"}],"libelle":"Total"},"rang-level":1},{"serie":{"data":[{"valeur":"39104","annee":"2012"},{"valeur":"43672","annee":"2013"},{"valeur":"39068","annee":"2014"},{"valeur":"47474","annee":"2015"},{"valeur":"42069","annee":"2016"},{"valeur":"41612","annee":"2017"}],"libelle":"Plomb"},"rang-level":2},{"serie":{"data":[{"valeur":"91630","annee":"2012"},{"valeur":"82484","annee":"2013"},{"valeur":"89570","annee":"2014"},{"valeur":"106005","annee":"2015"},{"valeur":"106272","annee":"2016"},{"valeur":"105971","annee":"2017"}],"libelle":"Zinc"},"rang-level":3},{"serie":{"data":[{"valeur":"170","annee":"2012"},{"valeur":"194","annee":"2013"},{"valeur":"186","annee":"2014"},{"valeur":"231","annee":"2015"},{"valeur":"222","annee":"2016"},{"valeur":"222","annee":"2017"}],"libelle":"Argent brut"},"rang-level":4},{"serie":{"data":[{"valeur":"58969","annee":"2012"},{"valeur":"46319","annee":"2013"},{"valeur":"66481","annee":"2014"},{"valeur":"73165","annee":"2015"},{"valeur":"118760","annee":"2016"},{"valeur":"125885","annee":"2017"}],"libelle":"Cuivre"},"rang-level":5},{"serie":{"data":[{"valeur":"260695","annee":"2012"},{"valeur":"301053","annee":"2013"},{"valeur":"22911","annee":"2014"},{"valeur":"17976","annee":"2015"},{"valeur":"21033","annee":"2016"},{"valeur":null,"annee":"2017"}],"libelle":"Fer"},"rang-level":6},{"serie":{"data":[{"valeur":"90185","annee":"2012"},{"valeur":"110947","annee":"2013"},{"valeur":"91271","annee":"2014"},{"valeur":"72602","annee":"2015"},{"valeur":"70138","annee":"2016"},{"valeur":"94500","annee":"2017"}],"libelle":"Manganèse chimique"},"rang-level":7},{"serie":{"data":[{"valeur":"79278","annee":"2012"},{"valeur":"81246","annee":"2013"},{"valeur":"79842","annee":"2014"},{"valeur":"80887","annee":"2015"},{"valeur":"74276","annee":"2016"},{"valeur":"59204","annee":"2017"}],"libelle":"Fluorine"},"rang-level":8},{"serie":{"data":[{"valeur":"1021410","annee":"2012"},{"valeur":"1094468","annee":"2013"},{"valeur":"1006601","annee":"2014"},{"valeur":"1212799","annee":"2015"},{"valeur":"676940","annee":"2016"},{"valeur":"971051","annee":"2017"}],"libelle":"Barytine"},"rang-level":9},{"serie":{"data":[{"valeur":"144231","annee":"2012"},{"valeur":"488294","annee":"2013"},{"valeur":"439155","annee":"2014"},{"valeur":"555759","annee":"2015"},{"valeur":"634662","annee":"2016"},{"valeur":"704765","annee":"2017"}],"libelle":"Sel"},"rang-level":10},{"serie":{"data":[{"valeur":"1889","annee":"2012"},{"valeur":"1994","annee":"2013"},{"valeur":"809","annee":"2014"},{"valeur":"1466","annee":"2015"},{"valeur":"908","annee":"2016"},{"valeur":"840","annee":"2017"}],"libelle":"Ghassoul"},"rang-level":11},{"serie":{"data":[{"valeur":"81820","annee":"2012"},{"valeur":"59000","annee":"2013"},{"valeur":"73500","annee":"2014"},{"valeur":"84569","annee":"2015"},{"valeur":"141760","annee":"2016"},{"valeur":"104140","annee":"2017"}],"libelle":"Argiles smectiques"},"rang-level":12},{"serie":{"data":[{"valeur":"20041","annee":"2012"},{"valeur":"20325","annee":"2013"},{"valeur":"21507","annee":"2014"},{"valeur":"22464","annee":"2015"},{"valeur":"23897","annee":"2016"},{"valeur":"28987","annee":"2017"}],"libelle":"Colbat"},"rang-level":13},{"serie":{"data":[{"valeur":"91163","annee":"2012"},{"valeur":"105239","annee":"2013"},{"valeur":"98757","annee":"2014"},{"valeur":"92287","annee":"2015"},{"valeur":"103266","annee":"2016"},{"valeur":"103960","annee":"2017"}],"libelle":"Bentonite"},"rang-level":14}],"dimensions":[{"libelle":"Produits Miniers","h":false,"modalites":[{"libelle":"Total","rang":1},{"libelle":"Plomb","rang":2},{"libelle":"Zinc","rang":3},{"libelle":"Argent brut","rang":4},{"libelle":"Cuivre","rang":5},{"libelle":"Fer","rang":6},{"libelle":"Manganèse chimique","rang":7},{"libelle":"Fluorine","rang":8},{"libelle":"Barytine","rang":9},{"libelle":"Sel","rang":10},{"libelle":"Ghassoul","rang":11},{"libelle":"Argiles smectiques","rang":12},{"libelle":"Colbat","rang":13},{"libelle":"Bentonite","rang":14}],"rang":1}]}