{"indLibelle":"Evolution de l'extraction des phosphates","metaData":{"decription":null,"periodicite":"Annuelle","unite":"MILLIERS DE TONNES","source":"MINISTERE DE L'ENERGIE ET DES MINES, DE L'EAU ET DE L'ENVIRONNEMENT "},"periodes":["2013","2014","2015","2016"],"levels":[{"serie":null,"rang-level":1},{"serie":{"data":[{"valeur":"5309","annee":"2013"},{"valeur":"6049","annee":"2014"},{"valeur":"3767","annee":"2015"},{"valeur":"3786","annee":"2016"}],"libelle":"Benguerir"},"rang-level":2},{"serie":{"data":[{"valeur":"2098","annee":"2013"},{"valeur":"1816","annee":"2014"},{"valeur":"1607","annee":"2015"},{"valeur":"1857","annee":"2016"}],"libelle":"Boucrâa"},"rang-level":3},{"serie":{"data":[{"valeur":"18507","annee":"2013"},{"valeur":"20538","annee":"2014"},{"valeur":"21442","annee":"2015"},{"valeur":"22166","annee":"2016"}],"libelle":"Khouribga"},"rang-level":4},{"serie":{"data":[{"valeur":"2890","annee":"2013"},{"valeur":"3615","annee":"2014"},{"valeur":"3507","annee":"2015"},{"valeur":"3658","annee":"2016"}],"libelle":"Youssoufia"},"rang-level":5}],"dimensions":[{"libelle":"Centre d'exploitation","h":false,"modalites":[{"libelle":"Total","rang":1},{"libelle":"Benguerir","rang":2},{"libelle":"Boucrâa","rang":3},{"libelle":"Khouribga","rang":4},{"libelle":"Youssoufia","rang":5}],"rang":1}]}